globalmart_api/__init__.py
globalmart_api/process_json.py
DarCDTLib-0.1.dist-info/License.txt
DarCDTLib-0.1.dist-info/METADATA
DarCDTLib-0.1.dist-info/WHEEL
DarCDTLib-0.1.dist-info/top_level.txt
DarCDTLib-0.1.dist-info/RECORD
